[
  {
    "seq": 1,
    "Datelisted": "\"20230401\"",
    "year": "\"103\"",
    "type": "\"總計\"",
    "area": "\"-\"",
    "totalpercent": 100.0,
    "legislatorsAndManagerspercent": 0.92084897,
    "professionalspercent": 6.0912604,
    "technicianAndassistantTechnicianpercent": 5.367505,
    "clericalSupportWorkerpercent": 6.1542745,
    "serviceAndsalesWorkerpercent": 21.731274,
    "primaryIndustrialWorkerpercent": 6.4627843,
    "craftAndRelatedWorkerpercent": 20.359516,
    "machineryOperatorAndAssemblerpercent": 16.033833,
    "elementaryWorkerLaborerpercent": 16.878704,
    "sampleCount": 30225.586,
    "populationCount": 235643.11
  },
  {
    "seq": 2,
    "Datelisted": "\"20230401\"",
    "year": "\"103\"",
    "type": "\"行政區域\"",
    "area": "\"山地鄉\"",
    "totalpercent": 100.0,
    "legislatorsAndManagerspercent": 1.1128325,
    "professionalspercent": 6.620349,
    "technicianAndassistantTechnicianpercent": 5.004123,
    "clericalSupportWorkerpercent": 5.063382,
    "serviceAndsalesWorkerpercent": 17.797207,
    "primaryIndustrialWorkerpercent": 12.991075,
    "craftAndRelatedWorkerpercent": 16.989195,
    "machineryOperatorAndAssemblerpercent": 13.39951,
    "elementaryWorkerLaborerpercent": 21.022327,
    "sampleCount": 9266.379,
    "populationCount": 72242.85
  },
  {
    "seq": 3,
    "Datelisted": "\"20230401\"",
    "year": "\"103\"",
    "type": "\"行政區域\"",
    "area": "\"平地原住民鄉鎮市\"",
    "totalpercent": 100.0,
    "legislatorsAndManagerspercent": 0.8121592,
    "professionalspercent": 5.7060647,
    "technicianAndassistantTechnicianpercent": 4.827903,
    "clericalSupportWorkerpercent": 5.538325,
    "serviceAndsalesWorkerpercent": 22.77288,
    "primaryIndustrialWorkerpercent": 8.535867,
    "craftAndRelatedWorkerpercent": 23.34466,
    "machineryOperatorAndAssemblerpercent": 10.81884,
    "elementaryWorkerLaborerpercent": 17.6433,
    "sampleCount": 7541.8325,
    "populationCount": 58796.523
  },
  {
    "seq": 4,
    "Datelisted": "\"20230401\"",
    "year": "\"103\"",
    "type": "\"行政區域\"",
    "area": "\"非原住民鄉鎮市\"",
    "totalpercent": 100.0,
    "legislatorsAndManagerspercent": 0.8493519,
    "professionalspercent": 5.9423685,
    "technicianAndassistantTechnicianpercent": 5.9217725,
    "clericalSupportWorkerpercent": 7.253899,
    "serviceAndsalesWorkerpercent": 23.862799,
    "primaryIndustrialWorkerpercent": 0.78887314,
    "craftAndRelatedWorkerpercent": 21.009258,
    "machineryOperatorAndAssemblerpercent": 20.784472,
    "elementaryWorkerLaborerpercent": 13.587206,
    "sampleCount": 13417.375,
    "populationCount": 104603.734
  },
  {
    "seq": 5,
    "Datelisted": "\"20230401\"",
    "year": "\"103\"",
    "type": "\"統計區域\"",
    "area": "\"北部地區\"",
    "totalpercent": 100.0,
    "legislatorsAndManagerspercent": 0.79362625,
    "professionalspercent": 5.056998,
    "technicianAndassistantTechnicianpercent": 5.6519403,
    "clericalSupportWorkerpercent": 7.247029,
    "serviceAndsalesWorkerpercent": 23.1341,
    "primaryIndustrialWorkerpercent": 2.0620778,
    "craftAndRelatedWorkerpercent": 21.131464,
    "machineryOperatorAndAssemblerpercent": 19.995827,
    "elementaryWorkerLaborerpercent": 14.926938,
    "sampleCount": 10340.266,
    "populationCount": 80614.39
  },
  {
    "seq": 6,
    "Datelisted": "\"20230401\"",
    "year": "\"103\"",
    "type": "\"統計區域\"",
    "area": "\"北部地區_山地鄉\"",
    "totalpercent": 100.0,
    "legislatorsAndManagerspercent": 0.9756838,
    "professionalspercent": 4.869119,
    "technicianAndassistantTechnicianpercent": 3.666859,
    "clericalSupportWorkerpercent": 6.573062,
    "serviceAndsalesWorkerpercent": 20.1016,
    "primaryIndustrialWorkerpercent": 9.456042,
    "craftAndRelatedWorkerpercent": 17.082926,
    "machineryOperatorAndAssemblerpercent": 17.305094,
    "elementaryWorkerLaborerpercent": 19.969616,
    "sampleCount": 1739.9928,
    "populationCount": 13565.031
  },
  {
    "seq": 7,
    "Datelisted": "\"20230401\"",
    "year": "\"103\"",
    "type": "\"統計區域\"",
    "area": "\"北部地區_平地原住民鄉鎮市\"",
    "totalpercent": 100.0,
    "legislatorsAndManagerspercent": 0.0,
    "professionalspercent": 7.2434382,
    "technicianAndassistantTechnicianpercent": 4.3576603,
    "clericalSupportWorkerpercent": 0.0,
    "serviceAndsalesWorkerpercent": 9.62409,
    "primaryIndustrialWorkerpercent": 4.790564,
    "craftAndRelatedWorkerpercent": 20.003204,
    "machineryOperatorAndAssemblerpercent": 15.071209,
    "elementaryWorkerLaborerpercent": 38.909832,
    "sampleCount": 41.464428,
    "populationCount": 323.1881
  },
  {
    "seq": 8,
    "Datelisted": "\"20230401\"",
    "year": "\"103\"",
    "type": "\"統計區域\"",
    "area": "\"北部地區_非原住民鄉鎮市\"",
    "totalpercent": 100.0,
    "legislatorsAndManagerspercent": 0.760459,
    "professionalspercent": 5.0846024,
    "technicianAndassistantTechnicianpercent": 6.0617647,
    "clericalSupportWorkerpercent": 7.4191437,
    "serviceAndsalesWorkerpercent": 23.816025,
    "primaryIndustrialWorkerpercent": 0.5457138,
    "craftAndRelatedWorkerpercent": 21.959972,
    "machineryOperatorAndAssemblerpercent": 20.566689,
    "elementaryWorkerLaborerpercent": 13.785631,
    "sampleCount": 8558.809,
    "populationCount": 66726.17
  },
  {
    "seq": 9,
    "Datelisted": "\"20230401\"",
    "year": "\"103\"",
    "type": "\"統計區域\"",
    "area": "\"中部地區\"",
    "totalpercent": 100.0,
    "legislatorsAndManagerspercent": 1.25523,
    "professionalspercent": 5.9549885,
    "technicianAndassistantTechnicianpercent": 4.427641,
    "clericalSupportWorkerpercent": 5.2382917,
    "serviceAndsalesWorkerpercent": 18.310715,
    "primaryIndustrialWorkerpercent": 9.693472,
    "craftAndRelatedWorkerpercent": 16.435858,
    "machineryOperatorAndAssemblerpercent": 17.773561,
    "elementaryWorkerLaborerpercent": 20.910242,
    "sampleCount": 4499.238,
    "populationCount": 35077.406
  },
  {
    "seq": 10,
    "Datelisted": "\"20230401\"",
    "year": "\"103\"",
    "type": "\"統計區域\"",
    "area": "\"中部地區_山地鄉\"",
    "totalpercent": 100.0,
    "legislatorsAndManagerspercent": 0.7223024,
    "professionalspercent": 4.218099,
    "technicianAndassistantTechnicianpercent": 4.603364,
    "clericalSupportWorkerpercent": 3.5102177,
    "serviceAndsalesWorkerpercent": 12.052459,
    "primaryIndustrialWorkerpercent": 21.948486,
    "craftAndRelatedWorkerpercent": 9.490437,
    "machineryOperatorAndAssemblerpercent": 9.945228,
    "elementaryWorkerLaborerpercent": 33.509407,
    "sampleCount": 1862.3071,
    "populationCount": 14519.311
  },
  {
    "seq": 11,
    "Datelisted": "\"20230401\"",
    "year": "\"103\"",
    "type": "\"統計區域\"",
    "area": "\"中部地區_平地原住民鄉鎮市\"",
    "totalpercent": 100.0,
    "legislatorsAndManagerspercent": 4.8783402,
    "professionalspercent": 5.609044,
    "technicianAndassistantTechnicianpercent": 3.6049812,
    "clericalSupportWorkerpercent": 10.85865,
    "serviceAndsalesWorkerpercent": 22.409195,
    "primaryIndustrialWorkerpercent": 6.9751835,
    "craftAndRelatedWorkerpercent": 7.0350285,
    "machineryOperatorAndAssemblerpercent": 11.041767,
    "elementaryWorkerLaborerpercent": 27.58781,
    "sampleCount": 166.67853,
    "populationCount": 1299.6572
  },
  {
    "seq": 12,
    "Datelisted": "\"20230401\"",
    "year": "\"103\"",
    "type": "\"統計區域\"",
    "area": "\"中部地區_非原住民鄉鎮市\"",
    "totalpercent": 100.0,
    "legislatorsAndManagerspercent": 1.4125084,
    "professionalspercent": 7.2878094,
    "technicianAndassistantTechnicianpercent": 4.3506775,
    "clericalSupportWorkerpercent": 6.16183,
    "serviceAndsalesWorkerpercent": 22.752348,
    "primaryIndustrialWorkerpercent": 0.6376247,
    "craftAndRelatedWorkerpercent": 22.306562,
    "machineryOperatorAndAssemblerpercent": 24.129791,
    "elementaryWorkerLaborerpercent": 10.96085,
    "sampleCount": 2470.2522,
    "populationCount": 19258.44
  },
  {
    "seq": 13,
    "Datelisted": "\"20230401\"",
    "year": "\"103\"",
    "type": "\"統計區域\"",
    "area": "\"南部地區\"",
    "totalpercent": 100.0,
    "legislatorsAndManagerspercent": 0.67147785,
    "professionalspercent": 7.4008126,
    "technicianAndassistantTechnicianpercent": 5.6545725,
    "clericalSupportWorkerpercent": 6.227539,
    "serviceAndsalesWorkerpercent": 20.72228,
    "primaryIndustrialWorkerpercent": 9.255549,
    "craftAndRelatedWorkerpercent": 18.861723,
    "machineryOperatorAndAssemblerpercent": 15.348398,
    "elementaryWorkerLaborerpercent": 15.857646,
    "sampleCount": 5858.289,
    "populationCount": 45671.098
  },
  {
    "seq": 14,
    "Datelisted": "\"20230401\"",
    "year": "\"103\"",
    "type": "\"統計區域\"",
    "area": "\"南部地區_山地鄉\"",
    "totalpercent": 100.0,
    "legislatorsAndManagerspercent": 0.8342572,
    "professionalspercent": 7.2434697,
    "technicianAndassistantTechnicianpercent": 4.7640414,
    "clericalSupportWorkerpercent": 4.9473886,
    "serviceAndsalesWorkerpercent": 17.453596,
    "primaryIndustrialWorkerpercent": 14.663718,
    "craftAndRelatedWorkerpercent": 20.759436,
    "machineryOperatorAndAssemblerpercent": 13.535987,
    "elementaryWorkerLaborerpercent": 15.798105,
    "sampleCount": 3361.2666,
    "populationCount": 26204.889
  },
  {
    "seq": 15,
    "Datelisted": "\"20230401\"",
    "year": "\"103\"",
    "type": "\"統計區域\"",
    "area": "\"南部地區_平地原住民鄉鎮市\"",
    "totalpercent": 100.0,
    "legislatorsAndManagerspercent": 0.0,
    "professionalspercent": 6.672434,
    "technicianAndassistantTechnicianpercent": 2.3969452,
    "clericalSupportWorkerpercent": 13.161567,
    "serviceAndsalesWorkerpercent": 24.829851,
    "primaryIndustrialWorkerpercent": 4.9580317,
    "craftAndRelatedWorkerpercent": 16.292482,
    "machineryOperatorAndAssemblerpercent": 9.837174,
    "elementaryWorkerLaborerpercent": 21.851515,
    "sampleCount": 119.67697,
    "populationCount": 932.6248
  },
  {
    "seq": 16,
    "Datelisted": "\"20230401\"",
    "year": "\"103\"",
    "type": "\"統計區域\"",
    "area": "\"南部地區_非原住民鄉鎮市\"",
    "totalpercent": 100.0,
    "legislatorsAndManagerspercent": 0.47511122,
    "professionalspercent": 7.6599345,
    "technicianAndassistantTechnicianpercent": 7.077634,
    "clericalSupportWorkerpercent": 7.6886353,
    "serviceAndsalesWorkerpercent": 25.13722,
    "primaryIndustrialWorkerpercent": 1.8251208,
    "craftAndRelatedWorkerpercent": 16.307808,
    "machineryOperatorAndAssemblerpercent": 18.18832,
    "elementaryWorkerLaborerpercent": 15.640216,
    "sampleCount": 2377.3457,
    "populationCount": 18533.584
  },
  {
    "seq": 17,
    "Datelisted": "\"20230401\"",
    "year": "\"103\"",
    "type": "\"統計區域\"",
    "area": "\"東部地區\"",
    "totalpercent": 100.0,
    "legislatorsAndManagerspercent": 1.054341,
    "professionalspercent": 6.4728947,
    "technicianAndassistantTechnicianpercent": 5.326144,
    "clericalSupportWorkerpercent": 5.3558445,
    "serviceAndsalesWorkerpercent": 22.444496,
    "primaryIndustrialWorkerpercent": 7.9959984,
    "craftAndRelatedWorkerpercent": 22.295528,
    "machineryOperatorAndAssemblerpercent": 11.33387,
    "elementaryWorkerLaborerpercent": 17.720882,
    "sampleCount": 9527.794,
    "populationCount": 74280.21
  },
  {
    "seq": 18,
    "Datelisted": "\"20230401\"",
    "year": "\"103\"",
    "type": "\"統計區域\"",
    "area": "\"東部地區_山地鄉\"",
    "totalpercent": 100.0,
    "legislatorsAndManagerspercent": 1.9388883,
    "professionalspercent": 8.976737,
    "technicianAndassistantTechnicianpercent": 6.689027,
    "clericalSupportWorkerpercent": 5.348094,
    "serviceAndsalesWorkerpercent": 21.203472,
    "primaryIndustrialWorkerpercent": 5.976664,
    "craftAndRelatedWorkerpercent": 17.479712,
    "machineryOperatorAndAssemblerpercent": 13.042931,
    "elementaryWorkerLaborerpercent": 19.344475,
    "sampleCount": 2302.8123,
    "populationCount": 17953.62
  },
  {
    "seq": 19,
    "Datelisted": "\"20230401\"",
    "year": "\"103\"",
    "type": "\"統計區域\"",
    "area": "\"東部地區_平地原住民鄉鎮市\"",
    "totalpercent": 100.0,
    "legislatorsAndManagerspercent": 0.73632985,
    "professionalspercent": 5.6834474,
    "technicianAndassistantTechnicianpercent": 4.899177,
    "clericalSupportWorkerpercent": 5.3207912,
    "serviceAndsalesWorkerpercent": 22.822735,
    "primaryIndustrialWorkerpercent": 8.652784,
    "craftAndRelatedWorkerpercent": 23.8577,
    "machineryOperatorAndAssemblerpercent": 10.8055315,
    "elementaryWorkerLaborerpercent": 17.221504,
    "sampleCount": 7214.0127,
    "populationCount": 56241.055
  },
  {
    "seq": 20,
    "Datelisted": "\"20230401\"",
    "year": "\"103\"",
    "type": "\"統計區域\"",
    "area": "\"東部地區_非原住民鄉鎮市\"",
    "totalpercent": 100.0,
    "legislatorsAndManagerspercent": 24.487356,
    "professionalspercent": 0.0,
    "technicianAndassistantTechnicianpercent": 0.0,
    "clericalSupportWorkerpercent": 30.029438,
    "serviceAndsalesWorkerpercent": 34.232113,
    "primaryIndustrialWorkerpercent": 0.0,
    "craftAndRelatedWorkerpercent": 5.96691,
    "machineryOperatorAndAssemblerpercent": 0.0,
    "elementaryWorkerLaborerpercent": 5.2841835,
    "sampleCount": 10.968732,
    "populationCount": 85.53969
  },
  {
    "seq": 21,
    "Datelisted": "\"20230401\"",
    "year": "\"103\"",
    "type": "\"縣市\"",
    "area": "\"新北市\"",
    "totalpercent": 100.0,
    "legislatorsAndManagerspercent": 0.63141805,
    "professionalspercent": 4.473867,
    "technicianAndassistantTechnicianpercent": 6.1168914,
    "clericalSupportWorkerpercent": 8.310043,
    "serviceAndsalesWorkerpercent": 25.248602,
    "primaryIndustrialWorkerpercent": 0.65355974,
    "craftAndRelatedWorkerpercent": 22.972765,
    "machineryOperatorAndAssemblerpercent": 16.475822,
    "elementaryWorkerLaborerpercent": 15.117031,
    "sampleCount": 3249.6462,
    "populationCount": 25335.113
  },
  {
    "seq": 22,
    "Datelisted": "\"20230401\"",
    "year": "\"103\"",
    "type": "\"縣市\"",
    "area": "\"臺北市\"",
    "totalpercent": 100.0,
    "legislatorsAndManagerspercent": 1.7686182,
    "professionalspercent": 9.922553,
    "technicianAndassistantTechnicianpercent": 7.635524,
    "clericalSupportWorkerpercent": 13.62205,
    "serviceAndsalesWorkerpercent": 30.057491,
    "primaryIndustrialWorkerpercent": 0.0,
    "craftAndRelatedWorkerpercent": 13.624097,
    "machineryOperatorAndAssemblerpercent": 10.061938,
    "elementaryWorkerLaborerpercent": 13.307729,
    "sampleCount": 903.5907,
    "populationCount": 7044.4053
  },
  {
    "seq": 23,
    "Datelisted": "\"20230401\"",
    "year": "\"103\"",
    "type": "\"縣市\"",
    "area": "\"桃園市\"",
    "totalpercent": 100.0,
    "legislatorsAndManagerspercent": 0.72800964,
    "professionalspercent": 3.7401352,
    "technicianAndassistantTechnicianpercent": 5.879136,
    "clericalSupportWorkerpercent": 4.818962,
    "serviceAndsalesWorkerpercent": 20.900703,
    "primaryIndustrialWorkerpercent": 2.300472,
    "craftAndRelatedWorkerpercent": 20.46204,
    "machineryOperatorAndAssemblerpercent": 27.187235,
    "elementaryWorkerLaborerpercent": 13.983307,
    "sampleCount": 3403.9714,
    "populationCount": 26538.482
  },
  {
    "seq": 24,
    "Datelisted": "\"20230401\"",
    "year": "\"103\"",
    "type": "\"縣市\"",
    "area": "\"臺中市\"",
    "totalpercent": 100.0,
    "legislatorsAndManagerspercent": 0.9654244,
    "professionalspercent": 6.7601275,
    "technicianAndassistantTechnicianpercent": 4.8699803,
    "clericalSupportWorkerpercent": 5.6689286,
    "serviceAndsalesWorkerpercent": 20.838108,
    "primaryIndustrialWorkerpercent": 2.9909723,
    "craftAndRelatedWorkerpercent": 23.277864,
    "machineryOperatorAndAssemblerpercent": 21.092981,
    "elementaryWorkerLaborerpercent": 13.535613,
    "sampleCount": 1816.0269,
    "populationCount": 14158.399
  },
  {
    "seq": 25,
    "Datelisted": "\"20230401\"",
    "year": "\"103\"",
    "type": "\"縣市\"",
    "area": "\"臺南市\"",
    "totalpercent": 100.0,
    "legislatorsAndManagerspercent": 0.28950158,
    "professionalspercent": 9.369707,
    "technicianAndassistantTechnicianpercent": 12.2157755,
    "clericalSupportWorkerpercent": 8.894874,
    "serviceAndsalesWorkerpercent": 31.300585,
    "primaryIndustrialWorkerpercent": 1.1614906,
    "craftAndRelatedWorkerpercent": 12.184946,
    "machineryOperatorAndAssemblerpercent": 11.712004,
    "elementaryWorkerLaborerpercent": 12.871116,
    "sampleCount": 392.94922,
    "populationCount": 3063.9978
  },
  {
    "seq": 26,
    "Datelisted": "\"20230401\"",
    "year": "\"103\"",
    "type": "\"縣市\"",
    "area": "\"高雄市\"",
    "totalpercent": 100.0,
    "legislatorsAndManagerspercent": 0.45840845,
    "professionalspercent": 6.7316394,
    "technicianAndassistantTechnicianpercent": 4.6494284,
    "clericalSupportWorkerpercent": 7.648038,
    "serviceAndsalesWorkerpercent": 18.576508,
    "primaryIndustrialWorkerpercent": 11.902794,
    "craftAndRelatedWorkerpercent": 17.898624,
    "machineryOperatorAndAssemblerpercent": 19.006413,
    "elementaryWorkerLaborerpercent": 13.128148,
    "sampleCount": 1790.2224,
    "populationCount": 13956.94
  },
  {
    "seq": 27,
    "Datelisted": "\"20230401\"",
    "year": "\"103\"",
    "type": "\"縣市\"",
    "area": "\"宜蘭縣\"",
    "totalpercent": 100.0,
    "legislatorsAndManagerspercent": 0.8879603,
    "professionalspercent": 5.3597417,
    "technicianAndassistantTechnicianpercent": 4.5690947,
    "clericalSupportWorkerpercent": 3.5478363,
    "serviceAndsalesWorkerpercent": 24.151426,
    "primaryIndustrialWorkerpercent": 6.2071824,
    "craftAndRelatedWorkerpercent": 26.815523,
    "machineryOperatorAndAssemblerpercent": 12.5093155,
    "elementaryWorkerLaborerpercent": 15.951919,
    "sampleCount": 733.0437,
    "populationCount": 5715.256
  },
  {
    "seq": 28,
    "Datelisted": "\"20230401\"",
    "year": "\"103\"",
    "type": "\"縣市\"",
    "area": "\"新竹縣\"",
    "totalpercent": 100.0,
    "legislatorsAndManagerspercent": 0.44697586,
    "professionalspercent": 6.230457,
    "technicianAndassistantTechnicianpercent": 3.110909,
    "clericalSupportWorkerpercent": 7.2914805,
    "serviceAndsalesWorkerpercent": 18.543188,
    "primaryIndustrialWorkerpercent": 5.5504174,
    "craftAndRelatedWorkerpercent": 12.347946,
    "machineryOperatorAndAssemblerpercent": 27.260122,
    "elementaryWorkerLaborerpercent": 19.218504,
    "sampleCount": 1119.7172,
    "populationCount": 8728.455
  },
  {
    "seq": 29,
    "Datelisted": "\"20230401\"",
    "year": "\"103\"",
    "type": "\"縣市\"",
    "area": "\"苗栗縣\"",
    "totalpercent": 100.0,
    "legislatorsAndManagerspercent": 1.0470855,
    "professionalspercent": 5.274042,
    "technicianAndassistantTechnicianpercent": 4.073797,
    "clericalSupportWorkerpercent": 3.4289358,
    "serviceAndsalesWorkerpercent": 15.19927,
    "primaryIndustrialWorkerpercent": 19.1881,
    "craftAndRelatedWorkerpercent": 12.612418,
    "machineryOperatorAndAssemblerpercent": 12.002823,
    "elementaryWorkerLaborerpercent": 27.173527,
    "sampleCount": 543.38385,
    "populationCount": 4236.553
  },
  {
    "seq": 30,
    "Datelisted": "\"20230401\"",
    "year": "\"103\"",
    "type": "\"縣市\"",
    "area": "\"彰化縣\"",
    "totalpercent": 100.0,
    "legislatorsAndManagerspercent": 2.9484956,
    "professionalspercent": 4.6888204,
    "technicianAndassistantTechnicianpercent": 2.8998678,
    "clericalSupportWorkerpercent": 2.8037205,
    "serviceAndsalesWorkerpercent": 21.088963,
    "primaryIndustrialWorkerpercent": 0.72855556,
    "craftAndRelatedWorkerpercent": 23.217442,
    "machineryOperatorAndAssemblerpercent": 33.483753,
    "elementaryWorkerLaborerpercent": 8.140382,
    "sampleCount": 388.90503,
    "populationCount": 3031.779
  },
  {
    "seq": 31,
    "Datelisted": "\"20230401\"",
    "year": "\"103\"",
    "type": "\"縣市\"",
    "area": "\"南投縣\"",
    "totalpercent": 100.0,
    "legislatorsAndManagerspercent": 1.3569529,
    "professionalspercent": 5.476228,
    "technicianAndassistantTechnicianpercent": 4.409048,
    "clericalSupportWorkerpercent": 5.8114595,
    "serviceAndsalesWorkerpercent": 14.097296,
    "primaryIndustrialWorkerpercent": 17.109518,
    "craftAndRelatedWorkerpercent": 8.826875,
    "machineryOperatorAndAssemblerpercent": 12.727148,
    "elementaryWorkerLaborerpercent": 30.185476,
    "sampleCount": 1605.5244,
    "populationCount": 12517.845
  },
  {
    "seq": 32,
    "Datelisted": "\"20230401\"",
    "year": "\"103\"",
    "type": "\"縣市\"",
    "area": "\"雲林縣\"",
    "totalpercent": 100.0,
    "legislatorsAndManagerspercent": 0.0,
    "professionalspercent": 7.117715,
    "technicianAndassistantTechnicianpercent": 4.5166917,
    "clericalSupportWorkerpercent": 6.804778,
    "serviceAndsalesWorkerpercent": 37.482,
    "primaryIndustrialWorkerpercent": 0.0,
    "craftAndRelatedWorkerpercent": 11.151908,
    "machineryOperatorAndAssemblerpercent": 11.586215,
    "elementaryWorkerLaborerpercent": 21.340693,
    "sampleCount": 145.39752,
    "populationCount": 1132.8323
  },
  {
    "seq": 33,
    "Datelisted": "\"20230401\"",
    "year": "\"103\"",
    "type": "\"縣市\"",
    "area": "\"嘉義縣\"",
    "totalpercent": 100.0,
    "legislatorsAndManagerspercent": 0.0,
    "professionalspercent": 5.9056177,
    "technicianAndassistantTechnicianpercent": 3.3286204,
    "clericalSupportWorkerpercent": 8.208066,
    "serviceAndsalesWorkerpercent": 18.043657,
    "primaryIndustrialWorkerpercent": 19.583088,
    "craftAndRelatedWorkerpercent": 7.463402,
    "machineryOperatorAndAssemblerpercent": 5.503086,
    "elementaryWorkerLaborerpercent": 31.964464,
    "sampleCount": 326.33466,
    "populationCount": 2544.7847
  },
  {
    "seq": 34,
    "Datelisted": "\"20230401\"",
    "year": "\"103\"",
    "type": "\"縣市\"",
    "area": "\"屏東縣\"",
    "totalpercent": 100.0,
    "legislatorsAndManagerspercent": 0.8459818,
    "professionalspercent": 7.6027527,
    "technicianAndassistantTechnicianpercent": 5.493069,
    "clericalSupportWorkerpercent": 4.935063,
    "serviceAndsalesWorkerpercent": 20.116755,
    "primaryIndustrialWorkerpercent": 8.25269,
    "craftAndRelatedWorkerpercent": 22.141006,
    "machineryOperatorAndAssemblerpercent": 15.024576,
    "elementaryWorkerLaborerpercent": 15.588104,
    "sampleCount": 3145.596,
    "populationCount": 24521.756
  },
  {
    "seq": 35,
    "Datelisted": "\"20230401\"",
    "year": "\"103\"",
    "type": "\"縣市\"",
    "area": "\"臺東縣\"",
    "totalpercent": 100.0,
    "legislatorsAndManagerspercent": 1.3316666,
    "professionalspercent": 5.467785,
    "technicianAndassistantTechnicianpercent": 5.391451,
    "clericalSupportWorkerpercent": 5.3010225,
    "serviceAndsalesWorkerpercent": 20.269644,
    "primaryIndustrialWorkerpercent": 10.666944,
    "craftAndRelatedWorkerpercent": 20.242924,
    "machineryOperatorAndAssemblerpercent": 10.464807,
    "elementaryWorkerLaborerpercent": 20.863758,
    "sampleCount": 4057.511,
    "populationCount": 31630.357
  },
  {
    "seq": 36,
    "Datelisted": "\"20230401\"",
    "year": "\"103\"",
    "type": "\"縣市\"",
    "area": "\"花蓮縣\"",
    "totalpercent": 100.0,
    "legislatorsAndManagerspercent": 0.8486683,
    "professionalspercent": 7.2183127,
    "technicianAndassistantTechnicianpercent": 5.277711,
    "clericalSupportWorkerpercent": 5.396502,
    "serviceAndsalesWorkerpercent": 24.05743,
    "primaryIndustrialWorkerpercent": 6.015149,
    "craftAndRelatedWorkerpercent": 23.8178,
    "machineryOperatorAndAssemblerpercent": 11.978392,
    "elementaryWorkerLaborerpercent": 15.390035,
    "sampleCount": 5470.2827,
    "populationCount": 42649.855
  },
  {
    "seq": 37,
    "Datelisted": "\"20230401\"",
    "year": "\"103\"",
    "type": "\"縣市\"",
    "area": "\"澎湖縣\"",
    "totalpercent": 100.0,
    "legislatorsAndManagerspercent": 2.0941775,
    "professionalspercent": 8.824469,
    "technicianAndassistantTechnicianpercent": 3.809258,
    "clericalSupportWorkerpercent": 7.8494964,
    "serviceAndsalesWorkerpercent": 36.229763,
    "primaryIndustrialWorkerpercent": 1.2965201,
    "craftAndRelatedWorkerpercent": 9.0478325,
    "machineryOperatorAndAssemblerpercent": 12.072742,
    "elementaryWorkerLaborerpercent": 18.775742,
    "sampleCount": 81.221306,
    "populationCount": 632.8458
  },
  {
    "seq": 38,
    "Datelisted": "\"20230401\"",
    "year": "\"103\"",
    "type": "\"縣市\"",
    "area": "\"基隆市\"",
    "totalpercent": 100.0,
    "legislatorsAndManagerspercent": 1.0525976,
    "professionalspercent": 5.534909,
    "technicianAndassistantTechnicianpercent": 3.8746512,
    "clericalSupportWorkerpercent": 9.619791,
    "serviceAndsalesWorkerpercent": 14.864771,
    "primaryIndustrialWorkerpercent": 0.8137503,
    "craftAndRelatedWorkerpercent": 37.192955,
    "machineryOperatorAndAssemblerpercent": 14.489326,
    "elementaryWorkerLaborerpercent": 12.557252,
    "sampleCount": 616.1069,
    "populationCount": 4803.32
  },
  {
    "seq": 39,
    "Datelisted": "\"20230401\"",
    "year": "\"103\"",
    "type": "\"縣市\"",
    "area": "\"新竹市\"",
    "totalpercent": 100.0,
    "legislatorsAndManagerspercent": 0.8856293,
    "professionalspercent": 5.5379343,
    "technicianAndassistantTechnicianpercent": 7.743402,
    "clericalSupportWorkerpercent": 8.044833,
    "serviceAndsalesWorkerpercent": 35.752197,
    "primaryIndustrialWorkerpercent": 0.32383728,
    "craftAndRelatedWorkerpercent": 17.470512,
    "machineryOperatorAndAssemblerpercent": 9.437817,
    "elementaryWorkerLaborerpercent": 14.803836,
    "sampleCount": 314.18985,
    "populationCount": 2449.357
  },
  {
    "seq": 40,
    "Datelisted": "\"20230401\"",
    "year": "\"103\"",
    "type": "\"縣市\"",
    "area": "\"嘉義市\"",
    "totalpercent": 100.0,
    "legislatorsAndManagerspercent": 1.3797925,
    "professionalspercent": 8.724998,
    "technicianAndassistantTechnicianpercent": 10.884464,
    "clericalSupportWorkerpercent": 3.7335522,
    "serviceAndsalesWorkerpercent": 30.596106,
    "primaryIndustrialWorkerpercent": 0.0,
    "craftAndRelatedWorkerpercent": 6.979474,
    "machineryOperatorAndAssemblerpercent": 10.252624,
    "elementaryWorkerLaborerpercent": 27.44899,
    "sampleCount": 121.96557,
    "populationCount": 950.77075
  },
  {
    "seq": 41,
    "Datelisted": "\"20230401\"",
    "year": "\"104\"",
    "type": "\"總計\"",
    "area": "\"-\"",
    "totalpercent": 100.0,
    "legislatorsAndManagerspercent": 0.70974785,
    "professionalspercent": 6.423962,
    "technicianAndassistantTechnicianpercent": 5.5597467,
    "clericalSupportWorkerpercent": 6.995549,
    "serviceAndsalesWorkerpercent": 22.096468,
    "primaryIndustrialWorkerpercent": 6.0302095,
    "craftAndRelatedWorkerpercent": 20.64576,
    "machineryOperatorAndAssemblerpercent": 17.032133,
    "elementaryWorkerLaborerpercent": 14.506425,
    "sampleCount": 30945.373,
    "populationCount": 237395.25
  },
  {
    "seq": 42,
    "Datelisted": "\"20230401\"",
    "year": "\"104\"",
    "type": "\"行政區域\"",
    "area": "\"山地鄉\"",
    "totalpercent": 100.0,
    "legislatorsAndManagerspercent": 0.972159,
    "professionalspercent": 7.6245365,
    "technicianAndassistantTechnicianpercent": 4.3959117,
    "clericalSupportWorkerpercent": 6.1207104,
    "serviceAndsalesWorkerpercent": 18.464823,
    "primaryIndustrialWorkerpercent": 12.006142,
    "craftAndRelatedWorkerpercent": 17.234043,
    "machineryOperatorAndAssemblerpercent": 14.219731,
    "elementaryWorkerLaborerpercent": 18.961943,
    "sampleCount": 9178.913,
    "populationCount": 70413.54
  },
  {
    "seq": 43,
    "Datelisted": "\"20230401\"",
    "year": "\"104\"",
    "type": "\"行政區域\"",
    "area": "\"平地原住名民鄉鎮市\"",
    "totalpercent": 100.0,
    "legislatorsAndManagerspercent": 0.69131136,
    "professionalspercent": 5.4162,
    "technicianAndassistantTechnicianpercent": 5.13802,
    "clericalSupportWorkerpercent": 6.0656905,
    "serviceAndsalesWorkerpercent": 23.267645,
    "primaryIndustrialWorkerpercent": 8.741911,
    "craftAndRelatedWorkerpercent": 23.053614,
    "machineryOperatorAndAssemblerpercent": 11.753363,
    "elementaryWorkerLaborerpercent": 15.872246,
    "sampleCount": 7690.404,
    "populationCount": 58995.035
  },
  {
    "seq": 44,
    "Datelisted": "\"20230401\"",
    "year": "\"104\"",
    "type": "\"行政區域\"",
    "area": "\"非原住民鄉鎮市\"",
    "totalpercent": 100.0,
    "legislatorsAndManagerspercent": 0.5487129,
    "professionalspercent": 6.191676,
    "technicianAndassistantTechnicianpercent": 6.549031,
    "clericalSupportWorkerpercent": 8.073993,
    "serviceAndsalesWorkerpercent": 23.824675,
    "primaryIndustrialWorkerpercent": 0.65210587,
    "craftAndRelatedWorkerpercent": 21.554943,
    "machineryOperatorAndAssemblerpercent": 21.749865,
    "elementaryWorkerLaborerpercent": 10.854998,
    "sampleCount": 14076.056,
    "populationCount": 107986.67
  },
  {
    "seq": 45,
    "Datelisted": "\"20230401\"",
    "year": "\"104\"",
    "type": "\"統計區域\"",
    "area": "\"北部地區\"",
    "totalpercent": 100.0,
    "legislatorsAndManagerspercent": 0.55928737,
    "professionalspercent": 5.5564218,
    "technicianAndassistantTechnicianpercent": 6.119911,
    "clericalSupportWorkerpercent": 8.0023155,
    "serviceAndsalesWorkerpercent": 23.616468,
    "primaryIndustrialWorkerpercent": 1.9308723,
    "craftAndRelatedWorkerpercent": 20.559195,
    "machineryOperatorAndAssemblerpercent": 21.361267,
    "elementaryWorkerLaborerpercent": 12.294261,
    "sampleCount": 10833.112,
    "populationCount": 83109.96
  },
  {
    "seq": 46,
    "Datelisted": "\"20230401\"",
    "year": "\"104\"",
    "type": "\"統計區域\"",
    "area": "\"北部地區_山地鄉\"",
    "totalpercent": 100.0,
    "legislatorsAndManagerspercent": 0.78940505,
    "professionalspercent": 8.663547,
    "technicianAndassistantTechnicianpercent": 2.7609057,
    "clericalSupportWorkerpercent": 6.3841577,
    "serviceAndsalesWorkerpercent": 19.944794,
    "primaryIndustrialWorkerpercent": 10.225046,
    "craftAndRelatedWorkerpercent": 11.8901615,
    "machineryOperatorAndAssemblerpercent": 19.163738,
    "elementaryWorkerLaborerpercent": 20.178246,
    "sampleCount": 1722.9774,
    "populationCount": 13218.287
  },
  {
    "seq": 47,
    "Datelisted": "\"20230401\"",
    "year": "\"104\"",
    "type": "\"統計區域\"",
    "area": "\"北部地區_平地原住民鄉鎮市\"",
    "totalpercent": 100.0,
    "legislatorsAndManagerspercent": 1.5535085,
    "professionalspercent": 3.0569649,
    "technicianAndassistantTechnicianpercent": 0.0,
    "clericalSupportWorkerpercent": 0.8387715,
    "serviceAndsalesWorkerpercent": 16.362703,
    "primaryIndustrialWorkerpercent": 0.8387715,
    "craftAndRelatedWorkerpercent": 10.877461,
    "machineryOperatorAndAssemblerpercent": 22.71515,
    "elementaryWorkerLaborerpercent": 43.756668,
    "sampleCount": 29.875166,
    "populationCount": 229.16655
  },
  {
    "seq": 48,
    "Datelisted": "\"20230401\"",
    "year": "\"104\"",
    "type": "\"統計區域\"",
    "area": "\"北部地區_非原住民鄉鎮市\"",
    "totalpercent": 100.0,
    "legislatorsAndManagerspercent": 0.51235247,
    "professionalspercent": 4.975075,
    "technicianAndassistantTechnicianpercent": 6.7774067,
    "clericalSupportWorkerpercent": 8.332923,
    "serviceAndsalesWorkerpercent": 24.33702,
    "primaryIndustrialWorkerpercent": 0.36066633,
    "craftAndRelatedWorkerpercent": 22.235973,
    "machineryOperatorAndAssemblerpercent": 21.77379,
    "elementaryWorkerLaborerpercent": 10.694794,
    "sampleCount": 9080.26,
    "populationCount": 69662.51
  },
  {
    "seq": 49,
    "Datelisted": "\"20230401\"",
    "year": "\"104\"",
    "type": "\"統計區域\"",
    "area": "\"中部地區\"",
    "totalpercent": 100.0,
    "legislatorsAndManagerspercent": 1.0814962,
    "professionalspercent": 7.2418776,
    "technicianAndassistantTechnicianpercent": 4.442626,
    "clericalSupportWorkerpercent": 5.6438355,
    "serviceAndsalesWorkerpercent": 18.346695,
    "primaryIndustrialWorkerpercent": 9.5143,
    "craftAndRelatedWorkerpercent": 18.336395,
    "machineryOperatorAndAssemblerpercent": 17.321898,
    "elementaryWorkerLaborerpercent": 18.070877,
    "sampleCount": 4621.448,
    "populationCount": 35453.715
  },
  {
    "seq": 50,
    "Datelisted": "\"20230401\"",
    "year": "\"104\"",
    "type": "\"統計區域\"",
    "area": "\"中部地區_山地鄉\"",
    "totalpercent": 100.0,
    "legislatorsAndManagerspercent": 1.550551,
    "professionalspercent": 6.179383,
    "technicianAndassistantTechnicianpercent": 4.0731745,
    "clericalSupportWorkerpercent": 3.5368984,
    "serviceAndsalesWorkerpercent": 15.63688,
    "primaryIndustrialWorkerpercent": 21.627552,
    "craftAndRelatedWorkerpercent": 8.926827,
    "machineryOperatorAndAssemblerpercent": 11.669717,
    "elementaryWorkerLaborerpercent": 26.799019,
    "sampleCount": 1837.4144,
    "populationCount": 14095.204
  },
  {
    "seq": 51,
    "Datelisted": "\"20230401\"",
    "year": "\"104\"",
    "type": "\"統計區域\"",
    "area": "\"中部地區_平地原住民鄉鎮市\"",
    "totalpercent": 100.0,
    "legislatorsAndManagerspercent": 0.94089156,
    "professionalspercent": 5.5090203,
    "technicianAndassistantTechnicianpercent": 2.3700275,
    "clericalSupportWorkerpercent": 4.615251,
    "serviceAndsalesWorkerpercent": 20.336407,
    "primaryIndustrialWorkerpercent": 7.731323,
    "craftAndRelatedWorkerpercent": 19.142094,
    "machineryOperatorAndAssemblerpercent": 12.674318,
    "elementaryWorkerLaborerpercent": 26.680668,
    "sampleCount": 182.27092,
    "populationCount": 1398.716
  },
  {
    "seq": 52,
    "Datelisted": "\"20230401\"",
    "year": "\"104\"",
    "type": "\"統計區域\"",
    "area": "\"中部地區_非原住民鄉鎮市\"",
    "totalpercent": 100.0,
    "legislatorsAndManagerspercent": 0.7601123,
    "professionalspercent": 8.113624,
    "technicianAndassistantTechnicianpercent": 4.8487663,
    "clericalSupportWorkerpercent": 7.203791,
    "serviceAndsalesWorkerpercent": 20.120878,
    "primaryIndustrialWorkerpercent": 1.0851121,
    "craftAndRelatedWorkerpercent": 24.92478,
    "machineryOperatorAndAssemblerpercent": 21.63904,
    "elementaryWorkerLaborerpercent": 11.303896,
    "sampleCount": 2601.7627,
    "populationCount": 19959.795
  },
  {
    "seq": 53,
    "Datelisted": "\"20230401\"",
    "year": "\"104\"",
    "type": "\"統計區域\"",
    "area": "\"南部地區\"",
    "totalpercent": 100.0,
    "legislatorsAndManagerspercent": 0.67039436,
    "professionalspercent": 8.107807,
    "technicianAndassistantTechnicianpercent": 5.36483,
    "clericalSupportWorkerpercent": 6.9699435,
    "serviceAndsalesWorkerpercent": 20.978718,
    "primaryIndustrialWorkerpercent": 7.0462704,
    "craftAndRelatedWorkerpercent": 20.94297,
    "machineryOperatorAndAssemblerpercent": 17.192478,
    "elementaryWorkerLaborerpercent": 12.726589,
    "sampleCount": 5738.4907,
    "populationCount": 44017.438
  },
  {
    "seq": 54,
    "Datelisted": "\"20230401\"",
    "year": "\"104\"",
    "type": "\"統計區域\"",
    "area": "\"南部地區_山地鄉\"",
    "totalpercent": 100.0,
    "legislatorsAndManagerspercent": 0.87317646,
    "professionalspercent": 7.692937,
    "technicianAndassistantTechnicianpercent": 3.8989308,
    "clericalSupportWorkerpercent": 6.2298703,
    "serviceAndsalesWorkerpercent": 16.880112,
    "primaryIndustrialWorkerpercent": 11.513397,
    "craftAndRelatedWorkerpercent": 25.199263,
    "machineryOperatorAndAssemblerpercent": 13.933702,
    "elementaryWorkerLaborerpercent": 13.778611,
    "sampleCount": 3213.3945,
    "populationCount": 24647.568
  },
  {
    "seq": 55,
    "Datelisted": "\"20230401\"",
    "year": "\"104\"",
    "type": "\"統計區域\"",
    "area": "\"南部地區_平地原住民鄉鎮市\"",
    "totalpercent": 100.0,
    "legislatorsAndManagerspercent": 0.0,
    "professionalspercent": 6.8835964,
    "technicianAndassistantTechnicianpercent": 1.922575,
    "clericalSupportWorkerpercent": 6.5109,
    "serviceAndsalesWorkerpercent": 31.559149,
    "primaryIndustrialWorkerpercent": 2.4951367,
    "craftAndRelatedWorkerpercent": 18.225424,
    "machineryOperatorAndAssemblerpercent": 12.666787,
    "elementaryWorkerLaborerpercent": 19.736431,
    "sampleCount": 143.4655,
    "populationCount": 1100.6619
  },
  {
    "seq": 56,
    "Datelisted": "\"20230401\"",
    "year": "\"104\"",
    "type": "\"統計區域\"",
    "area": "\"南部地區_非原住民鄉鎮市\"",
    "totalpercent": 100.0,
    "legislatorsAndManagerspercent": 0.43720374,
    "professionalspercent": 8.741276,
    "technicianAndassistantTechnicianpercent": 7.5499063,
    "clericalSupportWorkerpercent": 7.996056,
    "serviceAndsalesWorkerpercent": 25.87084,
    "primaryIndustrialWorkerpercent": 1.2937183,
    "craftAndRelatedWorkerpercent": 15.364392,
    "machineryOperatorAndAssemblerpercent": 21.861656,
    "elementaryWorkerLaborerpercent": 10.884953,
    "sampleCount": 2381.6309,
    "populationCount": 18269.207
  },
  {
    "seq": 57,
    "Datelisted": "\"20230401\"",
    "year": "\"104\"",
    "type": "\"統計區域\"",
    "area": "\"東部地區\"",
    "totalpercent": 100.0,
    "legislatorsAndManagerspercent": 0.7238782,
    "professionalspercent": 6.0093956,
    "technicianAndassistantTechnicianpercent": 5.581541,
    "clericalSupportWorkerpercent": 6.532777,
    "serviceAndsalesWorkerpercent": 22.842539,
    "primaryIndustrialWorkerpercent": 8.33522,
    "craftAndRelatedWorkerpercent": 21.661446,
    "machineryOperatorAndAssemblerpercent": 11.9913,
    "elementaryWorkerLaborerpercent": 16.321905,
    "sampleCount": 9752.321,
    "populationCount": 74814.13
  },
  {
    "seq": 58,
    "Datelisted": "\"20230401\"",
    "year": "\"104\"",
    "type": "\"統計區域\"",
    "area": "\"東部地區_山地鄉\"",
    "totalpercent": 100.0,
    "legislatorsAndManagerspercent": 0.7934741,
    "professionalspercent": 7.8927884,
    "technicianAndassistantTechnicianpercent": 6.4774966,
    "clericalSupportWorkerpercent": 7.7598667,
    "serviceAndsalesWorkerpercent": 21.681574,
    "primaryIndustrialWorkerpercent": 6.590732,
    "craftAndRelatedWorkerpercent": 16.768284,
    "machineryOperatorAndAssemblerpercent": 13.008057,
    "elementaryWorkerLaborerpercent": 19.027729,
    "sampleCount": 2405.1267,
    "populationCount": 18452.48
  },
  {
    "seq": 59,
    "Datelisted": "\"20230401\"",
    "year": "\"104\"",
    "type": "\"統計區域\"",
    "area": "\"東部地區_平地原住民鄉鎮市\"",
    "totalpercent": 100.0,
    "legislatorsAndManagerspercent": 0.6951186,
    "professionalspercent": 5.3947973,
    "technicianAndassistantTechnicianpercent": 5.2906547,
    "clericalSupportWorkerpercent": 6.1143265,
    "serviceAndsalesWorkerpercent": 23.20644,
    "primaryIndustrialWorkerpercent": 8.921419,
    "craftAndRelatedWorkerpercent": 23.294888,
    "machineryOperatorAndAssemblerpercent": 11.667955,
    "elementaryWorkerLaborerpercent": 15.414402,
    "sampleCount": 7334.792,
    "populationCount": 56266.492
  },
  {
    "seq": 60,
    "Datelisted": "\"20230401\"",
    "year": "\"104\"",
    "type": "\"統計區域\"",
    "area": "\"東部地區_非原住民鄉鎮市\"",
    "totalpercent": 100.0,
    "legislatorsAndManagerspercent": 4.2334833,
    "professionalspercent": 4.202281,
    "technicianAndassistantTechnicianpercent": 3.842963,
    "clericalSupportWorkerpercent": 16.009981,
    "serviceAndsalesWorkerpercent": 32.79666,
    "primaryIndustrialWorkerpercent": 0.0,
    "craftAndRelatedWorkerpercent": 4.668504,
    "machineryOperatorAndAssemblerpercent": 6.0200653,
    "elementaryWorkerLaborerpercent": 28.22606,
    "sampleCount": 12.402664,
    "populationCount": 95.1629
  },
  {
    "seq": 61,
    "Datelisted": "\"20230401\"",
    "year": "\"104\"",
    "type": "\"縣市\"",
    "area": "\"新北市\"",
    "totalpercent": 100.0,
    "legislatorsAndManagerspercent": 0.64348245,
    "professionalspercent": 3.6006181,
    "technicianAndassistantTechnicianpercent": 7.366459,
    "clericalSupportWorkerpercent": 9.191906,
    "serviceAndsalesWorkerpercent": 26.590881,
    "primaryIndustrialWorkerpercent": 0.30920914,
    "craftAndRelatedWorkerpercent": 23.167747,
    "machineryOperatorAndAssemblerpercent": 18.89769,
    "elementaryWorkerLaborerpercent": 10.232005,
    "sampleCount": 3336.2283,
    "populationCount": 25598.326
  },
  {
    "seq": 62,
    "Datelisted": "\"20230401\"",
    "year": "\"104\"",
    "type": "\"縣市\"",
    "area": "\"臺北市\"",
    "totalpercent": 100.0,
    "legislatorsAndManagerspercent": 0.6888263,
    "professionalspercent": 10.65855,
    "technicianAndassistantTechnicianpercent": 6.270101,
    "clericalSupportWorkerpercent": 14.843827,
    "serviceAndsalesWorkerpercent": 28.38225,
    "primaryIndustrialWorkerpercent": 0.31561863,
    "craftAndRelatedWorkerpercent": 15.589378,
    "machineryOperatorAndAssemblerpercent": 11.643823,
    "elementaryWorkerLaborerpercent": 11.607626,
    "sampleCount": 932.63354,
    "populationCount": 7154.6685
  },
  {
    "seq": 63,
    "Datelisted": "\"20230401\"",
    "year": "\"104\"",
    "type": "\"縣市\"",
    "area": "\"桃園市\"",
    "totalpercent": 100.0,
    "legislatorsAndManagerspercent": 0.35063156,
    "professionalspercent": 4.393544,
    "technicianAndassistantTechnicianpercent": 6.5508447,
    "clericalSupportWorkerpercent": 6.0395155,
    "serviceAndsalesWorkerpercent": 21.550095,
    "primaryIndustrialWorkerpercent": 1.8128482,
    "craftAndRelatedWorkerpercent": 21.045677,
    "machineryOperatorAndAssemblerpercent": 26.5256,
    "elementaryWorkerLaborerpercent": 11.731244,
    "sampleCount": 3867.36,
    "populationCount": 29669.145
  },
  {
    "seq": 64,
    "Datelisted": "\"20230401\"",
    "year": "\"104\"",
    "type": "\"縣市\"",
    "area": "\"臺中市\"",
    "totalpercent": 100.0,
    "legislatorsAndManagerspercent": 0.534523,
    "professionalspercent": 7.1626086,
    "technicianAndassistantTechnicianpercent": 4.783802,
    "clericalSupportWorkerpercent": 6.047166,
    "serviceAndsalesWorkerpercent": 18.810234,
    "primaryIndustrialWorkerpercent": 3.9188676,
    "craftAndRelatedWorkerpercent": 25.73275,
    "machineryOperatorAndAssemblerpercent": 19.73701,
    "elementaryWorkerLaborerpercent": 13.273042,
    "sampleCount": 1910.4325,
    "populationCount": 14654.389
  },
  {
    "seq": 65,
    "Datelisted": "\"20230401\"",
    "year": "\"104\"",
    "type": "\"縣市\"",
    "area": "\"臺南市\"",
    "totalpercent": 100.0,
    "legislatorsAndManagerspercent": 0.87016517,
    "professionalspercent": 8.109552,
    "technicianAndassistantTechnicianpercent": 6.5594625,
    "clericalSupportWorkerpercent": 8.1448145,
    "serviceAndsalesWorkerpercent": 27.040752,
    "primaryIndustrialWorkerpercent": 1.1342169,
    "craftAndRelatedWorkerpercent": 14.172688,
    "machineryOperatorAndAssemblerpercent": 23.421415,
    "elementaryWorkerLaborerpercent": 10.546933,
    "sampleCount": 408.21356,
    "populationCount": 3131.8533
  },
  {
    "seq": 66,
    "Datelisted": "\"20230401\"",
    "year": "\"104\"",
    "type": "\"縣市\"",
    "area": "\"高雄市\"",
    "totalpercent": 100.0,
    "legislatorsAndManagerspercent": 0.45023054,
    "professionalspercent": 6.9810004,
    "technicianAndassistantTechnicianpercent": 5.9715066,
    "clericalSupportWorkerpercent": 8.123346,
    "serviceAndsalesWorkerpercent": 20.43203,
    "primaryIndustrialWorkerpercent": 7.594872,
    "craftAndRelatedWorkerpercent": 17.94349,
    "machineryOperatorAndAssemblerpercent": 21.86615,
    "elementaryWorkerLaborerpercent": 10.637374,
    "sampleCount": 1678.7808,
    "populationCount": 12875.393
  },
  {
    "seq": 67,
    "Datelisted": "\"20230401\"",
    "year": "\"104\"",
    "type": "\"縣市\"",
    "area": "\"宜蘭縣\"",
    "totalpercent": 100.0,
    "legislatorsAndManagerspercent": 1.0855967,
    "professionalspercent": 12.144391,
    "technicianAndassistantTechnicianpercent": 5.5530715,
    "clericalSupportWorkerpercent": 5.7410617,
    "serviceAndsalesWorkerpercent": 20.912699,
    "primaryIndustrialWorkerpercent": 9.978628,
    "craftAndRelatedWorkerpercent": 12.547594,
    "machineryOperatorAndAssemblerpercent": 16.43673,
    "elementaryWorkerLaborerpercent": 15.600228,
    "sampleCount": 704.18256,
    "populationCount": 5402.051
  },
  {
    "seq": 68,
    "Datelisted": "\"20230401\"",
    "year": "\"104\"",
    "type": "\"縣市\"",
    "area": "\"新竹縣\"",
    "totalpercent": 100.0,
    "legislatorsAndManagerspercent": 0.37275383,
    "professionalspercent": 7.747421,
    "technicianAndassistantTechnicianpercent": 3.256269,
    "clericalSupportWorkerpercent": 7.7819595,
    "serviceAndsalesWorkerpercent": 19.990963,
    "primaryIndustrialWorkerpercent": 4.433817,
    "craftAndRelatedWorkerpercent": 10.558949,
    "machineryOperatorAndAssemblerpercent": 25.49131,
    "elementaryWorkerLaborerpercent": 20.366556,
    "sampleCount": 1068.647,
    "populationCount": 8196.006
  },
  {
    "seq": 69,
    "Datelisted": "\"20230401\"",
    "year": "\"104\"",
    "type": "\"縣市\"",
    "area": "\"苗栗縣\"",
    "totalpercent": 100.0,
    "legislatorsAndManagerspercent": 0.90177065,
    "professionalspercent": 5.793686,
    "technicianAndassistantTechnicianpercent": 4.3280883,
    "clericalSupportWorkerpercent": 5.0653706,
    "serviceAndsalesWorkerpercent": 15.645224,
    "primaryIndustrialWorkerpercent": 17.656412,
    "craftAndRelatedWorkerpercent": 14.324498,
    "machineryOperatorAndAssemblerpercent": 10.4626875,
    "elementaryWorkerLaborerpercent": 25.822264,
    "sampleCount": 549.671,
    "populationCount": 4218.2554
  },
  {
    "seq": 70,
    "Datelisted": "\"20230401\"",
    "year": "\"104\"",
    "type": "\"縣市\"",
    "area": "\"彰化縣\"",
    "totalpercent": 100.0,
    "legislatorsAndManagerspercent": 0.74327254,
    "professionalspercent": 5.0166807,
    "technicianAndassistantTechnicianpercent": 5.3248324,
    "clericalSupportWorkerpercent": 6.1448164,
    "serviceAndsalesWorkerpercent": 18.179724,
    "primaryIndustrialWorkerpercent": 0.8203931,
    "craftAndRelatedWorkerpercent": 24.347618,
    "machineryOperatorAndAssemblerpercent": 28.831688,
    "elementaryWorkerLaborerpercent": 10.590976,
    "sampleCount": 439.6434,
    "populationCount": 3373.2844
  },
  {
    "seq": 71,
    "Datelisted": "\"20230401\"",
    "year": "\"104\"",
    "type": "\"縣市\"",
    "area": "\"南投縣\"",
    "totalpercent": 100.0,
    "legislatorsAndManagerspercent": 1.9706112,
    "professionalspercent": 8.467033,
    "technicianAndassistantTechnicianpercent": 3.6111412,
    "clericalSupportWorkerpercent": 4.623648,
    "serviceAndsalesWorkerpercent": 18.285961,
    "primaryIndustrialWorkerpercent": 16.502012,
    "craftAndRelatedWorkerpercent": 9.678364,
    "machineryOperatorAndAssemblerpercent": 13.410999,
    "elementaryWorkerLaborerpercent": 23.450228,
    "sampleCount": 1600.6768,
    "populationCount": 12279.836
  },
  {
    "seq": 72,
    "Datelisted": "\"20230401\"",
    "year": "\"104\"",
    "type": "\"縣市\"",
    "area": "\"雲林縣\"",
    "totalpercent": 100.0,
    "legislatorsAndManagerspercent": 0.0,
    "professionalspercent": 6.9530735,
    "technicianAndassistantTechnicianpercent": 7.371654,
    "clericalSupportWorkerpercent": 13.583181,
    "serviceAndsalesWorkerpercent": 24.717348,
    "primaryIndustrialWorkerpercent": 0.0,
    "craftAndRelatedWorkerpercent": 12.491006,
    "machineryOperatorAndAssemblerpercent": 20.276049,
    "elementaryWorkerLaborerpercent": 14.607687,
    "sampleCount": 121.02426,
    "populationCount": 927.9514
  },
  {
    "seq": 73,
    "Datelisted": "\"20230401\"",
    "year": "\"104\"",
    "type": "\"縣市\"",
    "area": "\"嘉義縣\"",
    "totalpercent": 100.0,
    "legislatorsAndManagerspercent": 0.34430367,
    "professionalspercent": 4.3447537,
    "technicianAndassistantTechnicianpercent": 2.0057898,
    "clericalSupportWorkerpercent": 7.838476,
    "serviceAndsalesWorkerpercent": 21.952059,
    "primaryIndustrialWorkerpercent": 20.851755,
    "craftAndRelatedWorkerpercent": 6.2500696,
    "machineryOperatorAndAssemblerpercent": 8.624375,
    "elementaryWorkerLaborerpercent": 27.788418,
    "sampleCount": 298.10233,
    "populationCount": 2287.6133
  },
  {
    "seq": 74,
    "Datelisted": "\"20230401\"",
    "year": "\"104\"",
    "type": "\"縣市\"",
    "area": "\"屏東縣\"",
    "totalpercent": 100.0,
    "legislatorsAndManagerspercent": 0.80329233,
    "professionalspercent": 9.046165,
    "technicianAndassistantTechnicianpercent": 5.0988984,
    "clericalSupportWorkerpercent": 6.145947,
    "serviceAndsalesWorkerpercent": 19.841324,
    "primaryIndustrialWorkerpercent": 6.537154,
    "craftAndRelatedWorkerpercent": 25.199574,
    "machineryOperatorAndAssemblerpercent": 15.022659,
    "elementaryWorkerLaborerpercent": 12.304987,
    "sampleCount": 3213.048,
    "populationCount": 24646.637
  },
  {
    "seq": 75,
    "Datelisted": "\"20230401\"",
    "year": "\"104\"",
    "type": "\"縣市\"",
    "area": "\"臺東縣\"",
    "totalpercent": 100.0,
    "legislatorsAndManagerspercent": 0.7847935,
    "professionalspercent": 5.334662,
    "technicianAndassistantTechnicianpercent": 5.1587076,
    "clericalSupportWorkerpercent": 5.0579057,
    "serviceAndsalesWorkerpercent": 24.524755,
    "primaryIndustrialWorkerpercent": 11.035152,
    "craftAndRelatedWorkerpercent": 21.107384,
    "machineryOperatorAndAssemblerpercent": 10.022318,
    "elementaryWorkerLaborerpercent": 16.974321,
    "sampleCount": 4039.9614,
    "populationCount": 31000.352
  },
  {
    "seq": 76,
    "Datelisted": "\"20230401\"",
    "year": "\"104\"",
    "type": "\"縣市\"",
    "area": "\"花蓮縣\"",
    "totalpercent": 100.0,
    "legislatorsAndManagerspercent": 0.68077767,
    "professionalspercent": 6.486802,
    "technicianAndassistantTechnicianpercent": 5.880716,
    "clericalSupportWorkerpercent": 7.5763187,
    "serviceAndsalesWorkerpercent": 21.652288,
    "primaryIndustrialWorkerpercent": 6.4248886,
    "craftAndRelatedWorkerpercent": 22.053473,
    "machineryOperatorAndAssemblerpercent": 13.384448,
    "elementaryWorkerLaborerpercent": 15.860288,
    "sampleCount": 5712.36,
    "populationCount": 43813.78
  },
  {
    "seq": 77,
    "Datelisted": "\"20230401\"",
    "year": "\"104\"",
    "type": "\"縣市\"",
    "area": "\"澎湖縣\"",
    "totalpercent": 100.0,
    "legislatorsAndManagerspercent": 1.4823091,
    "professionalspercent": 14.467323,
    "technicianAndassistantTechnicianpercent": 3.7498841,
    "clericalSupportWorkerpercent": 9.368409,
    "serviceAndsalesWorkerpercent": 33.844585,
    "primaryIndustrialWorkerpercent": 0.0,
    "craftAndRelatedWorkerpercent": 15.856425,
    "machineryOperatorAndAssemblerpercent": 12.248935,
    "elementaryWorkerLaborerpercent": 8.98213,
    "sampleCount": 35.257442,
    "populationCount": 270.40985
  },
  {
    "seq": 78,
    "Datelisted": "\"20230401\"",
    "year": "\"104\"",
    "type": "\"縣市\"",
    "area": "\"基隆市\"",
    "totalpercent": 100.0,
    "legislatorsAndManagerspercent": 0.17627524,
    "professionalspercent": 5.0694838,
    "technicianAndassistantTechnicianpercent": 1.2279948,
    "clericalSupportWorkerpercent": 7.258179,
    "serviceAndsalesWorkerpercent": 15.97466,
    "primaryIndustrialWorkerpercent": 1.2247064,
    "craftAndRelatedWorkerpercent": 39.918945,
    "machineryOperatorAndAssemblerpercent": 17.85478,
    "elementaryWorkerLaborerpercent": 11.294975,
    "sampleCount": 608.84235,
    "populationCount": 4671.5903
  },
  {
    "seq": 79,
    "Datelisted": "\"20230401\"",
    "year": "\"104\"",
    "type": "\"縣市\"",
    "area": "\"新竹市\"",
    "totalpercent": 100.0,
    "legislatorsAndManagerspercent": 2.041204,
    "professionalspercent": 4.22964,
    "technicianAndassistantTechnicianpercent": 7.6152763,
    "clericalSupportWorkerpercent": 6.4854975,
    "serviceAndsalesWorkerpercent": 36.473206,
    "primaryIndustrialWorkerpercent": 0.22732282,
    "craftAndRelatedWorkerpercent": 16.072193,
    "machineryOperatorAndAssemblerpercent": 16.605976,
    "elementaryWorkerLaborerpercent": 10.249682,
    "sampleCount": 315.21857,
    "populationCount": 2418.1753
  },
  {
    "seq": 80,
    "Datelisted": "\"20230401\"",
    "year": "\"104\"",
    "type": "\"縣市\"",
    "area": "\"嘉義市\"",
    "totalpercent": 100.0,
    "legislatorsAndManagerspercent": 0.0,
    "professionalspercent": 5.952681,
    "technicianAndassistantTechnicianpercent": 9.241249,
    "clericalSupportWorkerpercent": 5.906389,
    "serviceAndsalesWorkerpercent": 33.86543,
    "primaryIndustrialWorkerpercent": 0.0,
    "craftAndRelatedWorkerpercent": 8.4036665,
    "machineryOperatorAndAssemblerpercent": 10.653407,
    "elementaryWorkerLaborerpercent": 25.977179,
    "sampleCount": 105.08871,
    "populationCount": 805.5327
  },
  {
    "seq": 81,
    "Datelisted": "\"20230401\"",
    "year": "\"106\"",
    "type": "\"總計\"",
    "area": "\"-\"",
    "totalpercent": 100.0,
    "legislatorsAndManagerspercent": 0.90855235,
    "professionalspercent": 7.862618,
    "technicianAndassistantTechnicianpercent": 5.9496737,
    "clericalSupportWorkerpercent": 7.390365,
    "serviceAndsalesWorkerpercent": 23.003784,
    "primaryIndustrialWorkerpercent": 7.10868,
    "craftAndRelatedWorkerpercent": 18.181944,
    "machineryOperatorAndAssemblerpercent": 14.478592,
    "elementaryWorkerLaborerpercent": 15.115791,
    "sampleCount": 28985.973,
    "populationCount": 248676.47
  },
  {
    "seq": 82,
    "Datelisted": "\"20230401\"",
    "year": "\"106\"",
    "type": "\"行政區域\"",
    "area": "\"山地原住民地區\"",
    "totalpercent": 100.0,
    "legislatorsAndManagerspercent": 1.2683718,
    "professionalspercent": 8.165064,
    "technicianAndassistantTechnicianpercent": 4.4743276,
    "clericalSupportWorkerpercent": 6.4624276,
    "serviceAndsalesWorkerpercent": 19.641417,
    "primaryIndustrialWorkerpercent": 14.925248,
    "craftAndRelatedWorkerpercent": 15.048805,
    "machineryOperatorAndAssemblerpercent": 12.979686,
    "elementaryWorkerLaborerpercent": 17.034655,
    "sampleCount": 8384.442,
    "populationCount": 71932.0
  },
  {
    "seq": 83,
    "Datelisted": "\"20230401\"",
    "year": "\"106\"",
    "type": "\"行政區域\"",
    "area": "\"平地原住民地區\"",
    "totalpercent": 100.0,
    "legislatorsAndManagerspercent": 0.7658509,
    "professionalspercent": 6.385718,
    "technicianAndassistantTechnicianpercent": 4.863388,
    "clericalSupportWorkerpercent": 6.4057765,
    "serviceAndsalesWorkerpercent": 24.3185,
    "primaryIndustrialWorkerpercent": 8.715764,
    "craftAndRelatedWorkerpercent": 22.986902,
    "machineryOperatorAndAssemblerpercent": 11.195526,
    "elementaryWorkerLaborerpercent": 14.362574,
    "sampleCount": 6872.1006,
    "populationCount": 58958.906
  },
  {
    "seq": 84,
    "Datelisted": "\"20230401\"",
    "year": "\"106\"",
    "type": "\"行政區域\"",
    "area": "\"非原住民地區\"",
    "totalpercent": 100.0,
    "legislatorsAndManagerspercent": 0.7602403,
    "professionalspercent": 8.417192,
    "technicianAndassistantTechnicianpercent": 7.394424,
    "clericalSupportWorkerpercent": 8.449906,
    "serviceAndsalesWorkerpercent": 24.399096,
    "primaryIndustrialWorkerpercent": 1.5306333,
    "craftAndRelatedWorkerpercent": 17.690186,
    "machineryOperatorAndAssemblerpercent": 17.037354,
    "elementaryWorkerLaborerpercent": 14.320968,
    "sampleCount": 13729.429,
    "populationCount": 117785.555
  },
  {
    "seq": 85,
    "Datelisted": "\"20230401\"",
    "year": "\"106\"",
    "type": "\"統計區域\"",
    "area": "\"北部地區\"",
    "totalpercent": 100.0,
    "legislatorsAndManagerspercent": 0.83902186,
    "professionalspercent": 7.4575653,
    "technicianAndassistantTechnicianpercent": 6.867537,
    "clericalSupportWorkerpercent": 8.460851,
    "serviceAndsalesWorkerpercent": 23.378624,
    "primaryIndustrialWorkerpercent": 2.670809,
    "craftAndRelatedWorkerpercent": 18.03338,
    "machineryOperatorAndAssemblerpercent": 16.998064,
    "elementaryWorkerLaborerpercent": 15.2941475,
    "sampleCount": 10248.497,
    "populationCount": 87924.13
  },
  {
    "seq": 86,
    "Datelisted": "\"20230401\"",
    "year": "\"106\"",
    "type": "\"統計區域\"",
    "area": "\"北部地區_山地原住民地區\"",
    "totalpercent": 100.0,
    "legislatorsAndManagerspercent": 1.0940158,
    "professionalspercent": 7.1784973,
    "technicianAndassistantTechnicianpercent": 3.5370457,
    "clericalSupportWorkerpercent": 8.156237,
    "serviceAndsalesWorkerpercent": 20.95227,
    "primaryIndustrialWorkerpercent": 11.108176,
    "craftAndRelatedWorkerpercent": 13.774875,
    "machineryOperatorAndAssemblerpercent": 16.07256,
    "elementaryWorkerLaborerpercent": 18.126324,
    "sampleCount": 1539.6652,
    "populationCount": 13210.545
  },
  {
    "seq": 87,
    "Datelisted": "\"20230401\"",
    "year": "\"106\"",
    "type": "\"統計區域\"",
    "area": "\"北部地區_平地原住民地區\"",
    "totalpercent": 100.0,
    "legislatorsAndManagerspercent": 0.0,
    "professionalspercent": 0.0,
    "technicianAndassistantTechnicianpercent": 0.0,
    "clericalSupportWorkerpercent": 5.2259965,
    "serviceAndsalesWorkerpercent": 1.2167048,
    "primaryIndustrialWorkerpercent": 7.7501354,
    "craftAndRelatedWorkerpercent": 0.0,
    "machineryOperatorAndAssemblerpercent": 38.302757,
    "elementaryWorkerLaborerpercent": 47.504402,
    "sampleCount": 22.60577,
    "populationCount": 193.92752
  },
  {
    "seq": 88,
    "Datelisted": "\"20230401\"",
    "year": "\"106\"",
    "type": "\"統計區域\"",
    "area": "\"北部地區_非原住民地區\"",
    "totalpercent": 100.0,
    "legislatorsAndManagerspercent": 0.79600096,
    "professionalspercent": 7.5264444,
    "technicianAndassistantTechnicianpercent": 7.475825,
    "clericalSupportWorkerpercent": 8.523271,
    "serviceAndsalesWorkerpercent": 23.86643,
    "primaryIndustrialWorkerpercent": 1.1618483,
    "craftAndRelatedWorkerpercent": 18.835241,
    "machineryOperatorAndAssemblerpercent": 17.106691,
    "elementaryWorkerLaborerpercent": 14.708248,
    "sampleCount": 8686.227,
    "populationCount": 74519.664
  },
  {
    "seq": 89,
    "Datelisted": "\"20230401\"",
    "year": "\"106\"",
    "type": "\"統計區域\"",
    "area": "\"中部地區\"",
    "totalpercent": 100.0,
    "legislatorsAndManagerspercent": 0.840898,
    "professionalspercent": 8.173783,
    "technicianAndassistantTechnicianpercent": 5.9860206,
    "clericalSupportWorkerpercent": 6.542235,
    "serviceAndsalesWorkerpercent": 22.055447,
    "primaryIndustrialWorkerpercent": 14.422564,
    "craftAndRelatedWorkerpercent": 12.660169,
    "machineryOperatorAndAssemblerpercent": 14.192242,
    "elementaryWorkerLaborerpercent": 15.126643,
    "sampleCount": 4459.607,
    "populationCount": 38252.305
  },
  {
    "seq": 90,
    "Datelisted": "\"20230401\"",
    "year": "\"106\"",
    "type": "\"統計區域\"",
    "area": "\"中部地區_山地原住民地區\"",
    "totalpercent": 100.0,
    "legislatorsAndManagerspercent": 0.9637296,
    "professionalspercent": 6.7095685,
    "technicianAndassistantTechnicianpercent": 4.2326064,
    "clericalSupportWorkerpercent": 5.2197056,
    "serviceAndsalesWorkerpercent": 16.150513,
    "primaryIndustrialWorkerpercent": 32.70706,
    "craftAndRelatedWorkerpercent": 6.130909,
    "machineryOperatorAndAssemblerpercent": 10.2895975,
    "elementaryWorkerLaborerpercent": 17.59631,
    "sampleCount": 1774.026,
    "populationCount": 15216.342
  },
  {
    "seq": 91,
    "Datelisted": "\"20230401\"",
    "year": "\"106\"",
    "type": "\"統計區域\"",
    "area": "\"中部地區_平地原住民地區\"",
    "totalpercent": 100.0,
    "legislatorsAndManagerspercent": 1.1530691,
    "professionalspercent": 2.9930887,
    "technicianAndassistantTechnicianpercent": 1.1006256,
    "clericalSupportWorkerpercent": 5.61454,
    "serviceAndsalesWorkerpercent": 27.042719,
    "primaryIndustrialWorkerpercent": 10.732416,
    "craftAndRelatedWorkerpercent": 11.52125,
    "machineryOperatorAndAssemblerpercent": 10.002614,
    "elementaryWorkerLaborerpercent": 29.839678,
    "sampleCount": 144.41725,
    "populationCount": 1239.2059
  },
  {
    "seq": 92,
    "Datelisted": "\"20230401\"",
    "year": "\"106\"",
    "type": "\"統計區域\"",
    "area": "\"中部地區_非原住民地區\"",
    "totalpercent": 100.0,
    "legislatorsAndManagerspercent": 0.7374013,
    "professionalspercent": 9.49049,
    "technicianAndassistantTechnicianpercent": 7.4878297,
    "clericalSupportWorkerpercent": 7.5182366,
    "serviceAndsalesWorkerpercent": 25.89415,
    "primaryIndustrialWorkerpercent": 1.8679272,
    "craftAndRelatedWorkerpercent": 17.283003,
    "machineryOperatorAndAssemblerpercent": 17.154875,
    "elementaryWorkerLaborerpercent": 12.56609,
    "sampleCount": 2541.1638,
    "populationCount": 21796.756
  },
  {
    "seq": 93,
    "Datelisted": "\"20230401\"",
    "year": "\"106\"",
    "type": "\"統計區域\"",
    "area": "\"南部地區\"",
    "totalpercent": 100.0,
    "legislatorsAndManagerspercent": 1.2632794,
    "professionalspercent": 9.590254,
    "technicianAndassistantTechnicianpercent": 5.965605,
    "clericalSupportWorkerpercent": 6.8427815,
    "serviceAndsalesWorkerpercent": 22.133486,
    "primaryIndustrialWorkerpercent": 8.354909,
    "craftAndRelatedWorkerpercent": 17.324018,
    "machineryOperatorAndAssemblerpercent": 14.151871,
    "elementaryWorkerLaborerpercent": 14.373796,
    "sampleCount": 5557.1714,
    "populationCount": 47682.98
  },
  {
    "seq": 94,
    "Datelisted": "\"20230401\"",
    "year": "\"106\"",
    "type": "\"統計區域\"",
    "area": "\"南部地區_山地原住民地區\"",
    "totalpercent": 100.0,
    "legislatorsAndManagerspercent": 1.8220128,
    "professionalspercent": 9.0478945,
    "technicianAndassistantTechnicianpercent": 5.2382693,
    "clericalSupportWorkerpercent": 5.1501126,
    "serviceAndsalesWorkerpercent": 19.939606,
    "primaryIndustrialWorkerpercent": 13.049473,
    "craftAndRelatedWorkerpercent": 19.93116,
    "machineryOperatorAndAssemblerpercent": 12.023934,
    "elementaryWorkerLaborerpercent": 13.797539,
    "sampleCount": 2947.7102,
    "populationCount": 25291.96
  },
  {
    "seq": 95,
    "Datelisted": "\"20230401\"",
    "year": "\"106\"",
    "type": "\"統計區域\"",
    "area": "\"南部地區_平地原住民地區\"",
    "totalpercent": 100.0,
    "legislatorsAndManagerspercent": 0.0,
    "professionalspercent": 4.656507,
    "technicianAndassistantTechnicianpercent": 2.3410807,
    "clericalSupportWorkerpercent": 2.9555542,
    "serviceAndsalesWorkerpercent": 25.287409,
    "primaryIndustrialWorkerpercent": 15.017876,
    "craftAndRelatedWorkerpercent": 18.221872,
    "machineryOperatorAndAssemblerpercent": 12.372789,
    "elementaryWorkerLaborerpercent": 19.146912,
    "sampleCount": 119.02914,
    "populationCount": 1022.0487
  },
  {
    "seq": 96,
    "Datelisted": "\"20230401\"",
    "year": "\"106\"",
    "type": "\"統計區域\"",
    "area": "\"南部地區_非原住民地區\"",
    "totalpercent": 100.0,
    "legislatorsAndManagerspercent": 0.6623927,
    "professionalspercent": 10.468156,
    "technicianAndassistantTechnicianpercent": 6.999823,
    "clericalSupportWorkerpercent": 9.032118,
    "serviceAndsalesWorkerpercent": 24.579277,
    "primaryIndustrialWorkerpercent": 2.4798205,
    "craftAndRelatedWorkerpercent": 14.195307,
    "machineryOperatorAndAssemblerpercent": 16.755552,
    "elementaryWorkerLaborerpercent": 14.827554,
    "sampleCount": 2490.432,
    "populationCount": 21368.97
  },
  {
    "seq": 97,
    "Datelisted": "\"20230401\"",
    "year": "\"106\"",
    "type": "\"統計區域\"",
    "area": "\"東部地區\"",
    "totalpercent": 100.0,
    "legislatorsAndManagerspercent": 0.7987765,
    "professionalspercent": 7.0784683,
    "technicianAndassistantTechnicianpercent": 4.8422737,
    "clericalSupportWorkerpercent": 6.914963,
    "serviceAndsalesWorkerpercent": 23.602806,
    "primaryIndustrialWorkerpercent": 7.7903314,
    "craftAndRelatedWorkerpercent": 21.726475,
    "machineryOperatorAndAssemblerpercent": 11.872371,
    "elementaryWorkerLaborerpercent": 15.373535,
    "sampleCount": 8720.696,
    "populationCount": 74817.05
  },
  {
    "seq": 98,
    "Datelisted": "\"20230401\"",
    "year": "\"106\"",
    "type": "\"統計區域\"",
    "area": "\"東部地區_山地原住民地區\"",
    "totalpercent": 100.0,
    "legislatorsAndManagerspercent": 0.8805317,
    "professionalspercent": 8.870699,
    "technicianAndassistantTechnicianpercent": 4.295255,
    "clericalSupportWorkerpercent": 8.094466,
    "serviceAndsalesWorkerpercent": 21.193037,
    "primaryIndustrialWorkerpercent": 5.442729,
    "craftAndRelatedWorkerpercent": 16.64341,
    "machineryOperatorAndAssemblerpercent": 14.311009,
    "elementaryWorkerLaborerpercent": 20.268862,
    "sampleCount": 2123.041,
    "populationCount": 18213.15
  },
  {
    "seq": 99,
    "Datelisted": "\"20230401\"",
    "year": "\"106\"",
    "type": "\"統計區域\"",
    "area": "\"東部地區_平地原住民地區\"",
    "totalpercent": 100.0,
    "legislatorsAndManagerspercent": 0.77384,
    "professionalspercent": 6.5133176,
    "technicianAndassistantTechnicianpercent": 5.0082264,
    "clericalSupportWorkerpercent": 6.489587,
    "serviceAndsalesWorkerpercent": 24.320517,
    "primaryIndustrialWorkerpercent": 8.560857,
    "craftAndRelatedWorkerpercent": 23.403444,
    "machineryOperatorAndAssemblerpercent": 11.107359,
    "elementaryWorkerLaborerpercent": 13.822852,
    "sampleCount": 6586.0483,
    "populationCount": 56503.723
  }
]